Metadata-Version: 2.1
Name: impedancetube
Version: 0.2.4
Summary: Library for Impedance/Transmission tube evaluation with the transfer function method
Home-page: https://github.com/tjueterb/impedancetube
Author: Tobias Jüterbock
Author-email: a.jueterbock@tu-berlin.de
License: BSD
Keywords: acoustic impedance transmission tube microphone measurement
Platform: UNKNOWN
Classifier: Development Status :: 3 - Alpha
Classifier: Intended Audience :: Education
Classifier: Intended Audience :: Science/Research
Classifier: Topic :: Scientific/Engineering :: Physics
Classifier: License :: OSI Approved :: BSD License
Classifier: Programming Language :: Python :: 3.7
Classifier: Programming Language :: Python :: 3.8
Classifier: Programming Language :: Python :: 3.9
License-File: LICENSE.txt
